setup.py
jasus/__init__.py
jasus.egg-info/PKG-INFO
jasus.egg-info/SOURCES.txt
jasus.egg-info/dependency_links.txt
jasus.egg-info/not-zip-safe
jasus.egg-info/top_level.txt