Metadata-Version: 1.0
Name: jasus
Version: 0.1
Summary: The funniest joke in the world
Home-page: https://github.com/Lokesh523s/funniest
Author: Flying Circus
Author-email: UNKNOWN
License: MIT
Platform: UNKNOWN
